meeshkan_tutorial/__init__.py
meeshkan_tutorial/tutorial.py
meeshkan_tutorial-0.0.5.dist-info/METADATA
meeshkan_tutorial-0.0.5.dist-info/WHEEL
meeshkan_tutorial-0.0.5.dist-info/entry_points.txt
meeshkan_tutorial-0.0.5.dist-info/top_level.txt
meeshkan_tutorial-0.0.5.dist-info/RECORD
