Metadata-Version: 2.1
Name: meeshkan-tutorial
Version: 0.0.5
Summary: A tutorial for Meeshkan
Home-page: https://github.com/meeshkan/meeshkan-tutorial
Author: Meeshkan
Author-email: mike@meeshkan.com
License: UNKNOWN
Keywords: meeshkan testing
Platform: UNKNOWN
Requires-Dist: meeshkan (>=0.2.13)
Requires-Dist: clint
Requires-Dist: pyfiglet
Requires-Dist: progress
Requires-Dist: http-types (>=0.0.11)
Provides-Extra: dev
Requires-Dist: setuptools ; extra == 'dev'
Requires-Dist: twine ; extra == 'dev'
Requires-Dist: wheel ; extra == 'dev'
